{
  "analysis_date": "2025-11-20 13:42:13",
  "total_stocks": 18,
  "successful_predictions": 12,
  "failed_predictions": 6,
  "timeframe": "daily",
  "pred_days": 5,
  "results": [
    {
      "stock_code": "000498",
      "timeframe": "daily",
      "prediction_date": "2025-11-20 13:42:25",
      "historical_data_points": 244,
      "pred_days": 5,
      "multi_model": {
        "technical": {
          "prices": [
            6.1131,
            6.0764214,
            6.0399628716,
            6.015803020113601,
            5.991739808033146
          ],
          "method": "technical_indicators",
          "signals": {
            "macd": -1,
            "rsi": 0,
            "ma": -1,
            "bollinger": 1
          }
        },
        "machine_learning": {
          "prices": [
            6.153600000000001,
            6.157600000000002,
            6.174400000000003,
            6.208000000000002,
            6.333200000000005
          ],
          "method": "machine_learning",
          "model_type": "RandomForest"
        },
        "support_resistance": {
          "prices": [
            6.127151515151516,
            6.104303030303031,
            6.081454545454546,
            6.058606060606062,
            6.035757575757577
          ],
          "method": "support_resistance",
          "support_levels": [
            5.35,
            5.37,
            5.49,
            5.59,
            5.66
          ],
          "resistance_levels": [
            6.58,
            6.5,
            6.46,
            6.34,
            6.33
          ],
          "next_support": 5.66,
          "next_resistance": 6.33
        },
        "ensemble": {
          "prices": [
            6.133515454545455,
            6.1172573290909105,
            6.1061852251163655,
            6.1055227242158985,
            6.1415292151372185
          ],
          "method": "ensemble",
          "weights": {
            "technical": 0.3,
            "ml": 0.4,
            "support_resistance": 0.3
          }
        },
        "confidence": {
          "overall_confidence": 0.9888472734834548,
          "price_consistency": 0.9888472734834548,
          "std_deviation": 0.06814468975630664
        }
      },
      "summary": {
        "current_price": 6.15,
        "predicted_prices": [
          6.133515454545455,
          6.1172573290909105,
          6.1061852251163655,
          6.1055227242158985,
          6.1415292151372185
        ],
        "price_changes": [
          -0.016484545454545696,
          -0.03274267090908989,
          -0.04381477488363483,
          -0.04447727578410188,
          -0.008470784862781855
        ],
        "price_change_pcts": [
          -0.26804138950480805,
          -0.5324011529933315,
          -0.712435363961542,
          -0.7232077363268598,
          -0.13773633923222528
        ],
        "confidence": 0.9888472734834548
      },
      "trading_signal": {
        "recommendation": "少量买入",
        "confidence": "中等",
        "score": 0,
        "details": {
          "kdj_score": 1,
          "macd_score": -1,
          "trend_score": 0,
          "pred_trend": 0.13065526044814912,
          "current_k": 31.773428560280927,
          "current_d": 46.5586857983245,
          "current_j": 2.202914084193779
        }
      }
    },
    {
      "stock_code": "600941",
      "timeframe": "daily",
      "prediction_date": "2025-11-20 13:42:27",
      "historical_data_points": 244,
      "pred_days": 5,
      "multi_model": {
        "technical": {
          "prices": [
            109.43268,
            109.87041072000001,
            110.30989236288,
            110.75113193233153,
            111.19413646006086
          ],
          "method": "technical_indicators",
          "signals": {
            "macd": 1,
            "rsi": 0,
            "ma": 1,
            "bollinger": -1
          }
        },
        "machine_learning": {
          "prices": [
            108.42079999999999,
            109.21059999999996,
            109.55019999999999,
            110.16479999999996,
            110.55879999999998
          ],
          "method": "machine_learning",
          "model_type": "RandomForest"
        },
        "support_resistance": {
          "prices": [
            108.81757575757577,
            108.85515151515153,
            108.8927272727273,
            108.93030303030307,
            108.96787878787883
          ],
          "method": "support_resistance",
          "support_levels": [
            103.8,
            104.6,
            105.12,
            105.29,
            105.5
          ],
          "resistance_levels": [
            119.51,
            118.68,
            116.1,
            114.81,
            114.69
          ],
          "next_support": 105.5,
          "next_resistance": 114.69
        },
        "ensemble": {
          "prices": [
            108.84339672727273,
            109.30190867054546,
            109.58086589068219,
            109.97035048879036,
            110.2721245743819
          ],
          "method": "ensemble",
          "weights": {
            "technical": 0.3,
            "ml": 0.4,
            "support_resistance": 0.3
          }
        },
        "confidence": {
          "overall_confidence": 0.994329758079987,
          "price_consistency": 0.994329758079987,
          "std_deviation": 0.6222467739315494
        }
      },
      "summary": {
        "current_price": 108.78,
        "predicted_prices": [
          108.84339672727273,
          109.30190867054546,
          109.58086589068219,
          109.97035048879036,
          110.2721245743819
        ],
        "price_changes": [
          0.06339672727273182,
          0.5219086705454572,
          0.8008658906821893,
          1.190350488790358,
          1.4921245743819043
        ],
        "price_change_pcts": [
          0.05827976399405389,
          0.4797836647779529,
          0.7362253085881497,
          1.094273293611287,
          1.3716901768541132
        ],
        "confidence": 0.994329758079987
      },
      "trading_signal": {
        "recommendation": "买入",
        "confidence": "较高",
        "score": 3,
        "details": {
          "kdj_score": 1,
          "macd_score": 1,
          "trend_score": 1,
          "pred_trend": 1.3126454062152382,
          "current_k": 64.02323475399956,
          "current_d": 59.18493503645646,
          "current_j": 73.69983418908576
        }
      }
    },
    {
      "stock_code": "002061",
      "timeframe": "daily",
      "prediction_date": "2025-11-20 13:42:31",
      "historical_data_points": 244,
      "pred_days": 5,
      "multi_model": {
        "technical": {
          "prices": [
            4.15492,
            4.12999048,
            4.11347051808,
            4.097016636007679,
            4.080628569463649
          ],
          "method": "technical_indicators",
          "signals": {
            "macd": -1,
            "rsi": 0,
            "ma": -1,
            "bollinger": 1
          }
        },
        "machine_learning": {
          "prices": [
            4.2749999999999995,
            4.288,
            4.3022,
            4.300399999999999,
            4.2928
          ],
          "method": "machine_learning",
          "model_type": "RandomForest"
        },
        "support_resistance": {
          "prices": [
            4.163818181818181,
            4.147636363636362,
            4.1314545454545435,
            4.115272727272725,
            4.099090909090906
          ],
          "method": "support_resistance",
          "support_levels": [
            3.56,
            3.69,
            3.76,
            3.82,
            3.83
          ],
          "resistance_levels": [
            4.55,
            4.5,
            4.42,
            4.4,
            4.33
          ],
          "next_support": 3.83,
          "next_resistance": 4.33
        },
        "ensemble": {
          "prices": [
            4.205621454545454,
            4.198488053090909,
            4.194357519060363,
            4.183846808984121,
            4.171035843566366
          ],
          "method": "ensemble",
          "weights": {
            "technical": 0.3,
            "ml": 0.4,
            "support_resistance": 0.3
          }
        },
        "confidence": {
          "overall_confidence": 0.9809327839249051,
          "price_consistency": 0.9809327839249051,
          "std_deviation": 0.07964213457117171
        }
      },
      "summary": {
        "current_price": 4.18,
        "predicted_prices": [
          4.205621454545454,
          4.198488053090909,
          4.194357519060363,
          4.183846808984121,
          4.171035843566366
        ],
        "price_changes": [
          0.025621454545454725,
          0.018488053090909062,
          0.014357519060363089,
          0.003846808984121708,
          -0.008964156433633796
        ],
        "price_change_pcts": [
          0.6129534580252327,
          0.442297920835145,
          0.34348131723356673,
          0.09202892306511264,
          -0.21445350319698078
        ],
        "confidence": 0.9809327839249051
      },
      "trading_signal": {
        "recommendation": "观望",
        "confidence": "谨慎",
        "score": -1,
        "details": {
          "kdj_score": 1,
          "macd_score": -1,
          "trend_score": -1,
          "pred_trend": -0.8223662389231022,
          "current_k": 17.80604103578986,
          "current_d": 32.909067236148346,
          "current_j": 0.0
        }
      }
    },
    {
      "stock_code": "002142",
      "timeframe": "daily",
      "prediction_date": "2025-11-20 13:42:33",
      "historical_data_points": 244,
      "pred_days": 5,
      "multi_model": {
        "technical": {
          "prices": [
            29.25,
            29.25,
            29.25,
            29.25,
            29.25
          ],
          "method": "technical_indicators",
          "signals": {
            "macd": -1,
            "rsi": 0,
            "ma": 1,
            "bollinger": 0
          }
        },
        "machine_learning": {
          "prices": [
            28.93499999999999,
            28.84399999999999,
            28.767799999999998,
            28.744600000000005,
            28.710200000000004
          ],
          "method": "machine_learning",
          "model_type": "RandomForest"
        },
        "support_resistance": {
          "prices": [
            29.19660606060606,
            29.143212121212123,
            29.089818181818185,
            29.036424242424246,
            28.983030303030308
          ],
          "method": "support_resistance",
          "support_levels": [
            22.82,
            23.46,
            23.48,
            23.63,
            23.75
          ],
          "resistance_levels": [
            29.63,
            29.44,
            29.16,
            29.07,
            28.82
          ],
          "next_support": 23.75,
          "next_resistance": 29.44
        },
        "ensemble": {
          "prices": [
            29.107981818181813,
            29.055563636363633,
            29.009065454545453,
            28.983767272727277,
            28.953989090909097
          ],
          "method": "ensemble",
          "weights": {
            "technical": 0.3,
            "ml": 0.4,
            "support_resistance": 0.3
          }
        },
        "confidence": {
          "overall_confidence": 0.9935428446940132,
          "price_consistency": 0.9935428446940132,
          "std_deviation": 0.18750671555960782
        }
      },
      "summary": {
        "current_price": 29.25,
        "predicted_prices": [
          29.107981818181813,
          29.055563636363633,
          29.009065454545453,
          28.983767272727277,
          28.953989090909097
        ],
        "price_changes": [
          -0.14201818181818737,
          -0.19443636363636685,
          -0.24093454545454662,
          -0.2662327272727225,
          -0.2960109090909029
        ],
        "price_change_pcts": [
          -0.48553224553226454,
          -0.6647397047397158,
          -0.8237078477078518,
          -0.9101973581973418,
          -1.0120031080030867
        ],
        "confidence": 0.9935428446940132
      },
      "trading_signal": {
        "recommendation": "少量买入",
        "confidence": "中等",
        "score": 0,
        "details": {
          "kdj_score": 0,
          "macd_score": 1,
          "trend_score": -1,
          "pred_trend": -0.5290395199316997,
          "current_k": 35.31714930973652,
          "current_d": 47.61696211619342,
          "current_j": 10.717523696822724
        }
      }
    },
    {
      "stock_code": "000544",
      "timeframe": "daily",
      "prediction_date": "2025-11-20 13:42:37",
      "historical_data_points": 244,
      "pred_days": 5,
      "multi_model": {
        "technical": {
          "prices": [
            8.71738,
            8.66507572,
            8.63041541712,
            8.59589375545152,
            8.561510180429714
          ],
          "method": "technical_indicators",
          "signals": {
            "macd": -1,
            "rsi": 0,
            "ma": -1,
            "bollinger": 1
          }
        },
        "machine_learning": {
          "prices": [
            8.834800000000001,
            8.724,
            8.673,
            8.623199999999999,
            8.594800000000003
          ],
          "method": "machine_learning",
          "model_type": "RandomForest"
        },
        "support_resistance": {
          "prices": [
            8.726303030303031,
            8.682606060606062,
            8.638909090909094,
            8.595212121212125,
            8.551515151515156
          ],
          "method": "support_resistance",
          "support_levels": [
            7.6,
            7.92,
            8.0,
            8.01,
            8.07
          ],
          "resistance_levels": [
            9.23,
            9.18,
            9.11,
            9.09,
            9.06
          ],
          "next_support": 8.07,
          "next_resistance": 9.06
        },
        "ensemble": {
          "prices": [
            8.76702490909091,
            8.693904534181819,
            8.649997352408729,
            8.606611762999094,
            8.571827599583463
          ],
          "method": "ensemble",
          "weights": {
            "technical": 0.3,
            "ml": 0.4,
            "support_resistance": 0.3
          }
        },
        "confidence": {
          "overall_confidence": 0.9970523362796857,
          "price_consistency": 0.9970523362796857,
          "std_deviation": 0.02560412936236714
        }
      },
      "summary": {
        "current_price": 8.77,
        "predicted_prices": [
          8.76702490909091,
          8.693904534181819,
          8.649997352408729,
          8.606611762999094,
          8.571827599583463
        ],
        "price_changes": [
          -0.0029750909090893174,
          -0.07609546581818094,
          -0.12000264759127077,
          -0.16338823700090543,
          -0.19817240041653683
        ],
        "price_change_pcts": [
          -0.033923499533515596,
          -0.867679199751208,
          -1.3683312154078766,
          -1.8630357696796516,
          -2.2596624904964293
        ],
        "confidence": 0.9970523362796857
      },
      "trading_signal": {
        "recommendation": "少量买入",
        "confidence": "中等",
        "score": 0,
        "details": {
          "kdj_score": 1,
          "macd_score": 1,
          "trend_score": -2,
          "pred_trend": -2.2264942957449447,
          "current_k": 23.096070539628137,
          "current_d": 41.210503865204004,
          "current_j": 0.0
        }
      }
    },
    {
      "stock_code": "601318",
      "timeframe": "daily",
      "prediction_date": "2025-11-20 13:42:39",
      "historical_data_points": 244,
      "pred_days": 5,
      "multi_model": {
        "technical": {
          "prices": [
            60.932759999999995,
            61.176491039999995,
            61.29884402208,
            61.42144171012416,
            61.544284593544404
          ],
          "method": "technical_indicators",
          "signals": {
            "macd": 1,
            "rsi": -1,
            "ma": 1,
            "bollinger": -1
          }
        },
        "machine_learning": {
          "prices": [
            59.39660000000001,
            58.851800000000004,
            58.730199999999996,
            58.92380000000001,
            59.14380000000001
          ],
          "method": "machine_learning",
          "model_type": "RandomForest"
        },
        "support_resistance": {
          "prices": [
            60.841272727272724,
            60.99254545454545,
            61.078509090909094,
            61.09570181818182,
            61.099140363636366
          ],
          "method": "support_resistance",
          "support_levels": [
            47.0,
            48.1,
            50.0,
            50.03,
            52.35
          ],
          "resistance_levels": [
            61.33,
            61.1,
            60.6,
            60.1,
            59.2
          ],
          "next_support": 52.35,
          "next_resistance": 61.1
        },
        "ensemble": {
          "prices": [
            60.29084981818182,
            60.19143094836364,
            60.205285933896725,
            60.324663058491794,
            60.45054748715423
          ],
          "method": "ensemble",
          "weights": {
            "technical": 0.3,
            "ml": 0.4,
            "support_resistance": 0.3
          }
        },
        "confidence": {
          "overall_confidence": 0.9832140121463504,
          "price_consistency": 0.9832140121463504,
          "std_deviation": 1.0144913544041474
        }
      },
      "summary": {
        "current_price": 60.69,
        "predicted_prices": [
          60.29084981818182,
          60.19143094836364,
          60.205285933896725,
          60.324663058491794,
          60.45054748715423
        ],
        "price_changes": [
          -0.39915018181817885,
          -0.498569051636359,
          -0.4847140661032725,
          -0.36533694150820395,
          -0.23945251284576585
        ],
        "price_change_pcts": [
          -0.6576869036384558,
          -0.8215011560987955,
          -0.7986720482835269,
          -0.6019722219611204,
          -0.3945501941765791
        ],
        "confidence": 0.9832140121463504
      },
      "trading_signal": {
        "recommendation": "少量买入",
        "confidence": "中等",
        "score": 1,
        "details": {
          "kdj_score": 0,
          "macd_score": 1,
          "trend_score": 0,
          "pred_trend": 0.26487878252506103,
          "current_k": 53.275787777001796,
          "current_d": 54.66536838481462,
          "current_j": 50.49662656137615
        }
      }
    },
    {
      "stock_code": "000001",
      "timeframe": "daily",
      "prediction_date": "2025-11-20 13:42:41",
      "historical_data_points": 244,
      "pred_days": 5,
      "multi_model": {
        "technical": {
          "prices": [
            11.90376,
            11.92756752,
            11.95142265504,
            11.97532550035008,
            11.999276151350779
          ],
          "method": "technical_indicators",
          "signals": {
            "macd": 1,
            "rsi": -1,
            "ma": 1,
            "bollinger": -1
          }
        },
        "machine_learning": {
          "prices": [
            11.659600000000003,
            11.773800000000001,
            11.762599999999997,
            11.760399999999995,
            11.769400000000001
          ],
          "method": "machine_learning",
          "model_type": "RandomForest"
        },
        "support_resistance": {
          "prices": [
            11.902909090909091,
            11.925818181818181,
            11.948727272727272,
            11.971636363636362,
            11.994545454545452
          ],
          "method": "support_resistance",
          "support_levels": [
            10.48,
            10.89,
            11.08,
            11.26,
            11.27
          ],
          "resistance_levels": [
            13.33,
            12.64,
            12.53,
            12.02,
            12.0
          ],
          "next_support": 11.27,
          "next_resistance": 12.0
        },
        "ensemble": {
          "prices": [
            11.805840727272729,
            11.865535710545455,
            11.87508497833018,
            11.88824855919593,
            11.90590648176887
          ],
          "method": "ensemble",
          "weights": {
            "technical": 0.3,
            "ml": 0.4,
            "support_resistance": 0.3
          }
        },
        "confidence": {
          "overall_confidence": 0.9918677055846042,
          "price_consistency": 0.9918677055846042,
          "std_deviation": 0.09661700404975485
        }
      },
      "summary": {
        "current_price": 11.88,
        "predicted_prices": [
          11.805840727272729,
          11.865535710545455,
          11.87508497833018,
          11.88824855919593,
          11.90590648176887
        ],
        "price_changes": [
          -0.07415927272727174,
          -0.01446428945454592,
          -0.004915021669820163,
          0.008248559195928706,
          0.025906481768869227
        ],
        "price_change_pcts": [
          -0.6242363024181122,
          -0.12175327823691852,
          -0.0413722362779475,
          0.06943231646404634,
          0.21806802835748507
        ],
        "confidence": 0.9918677055846042
      },
      "trading_signal": {
        "recommendation": "少量买入",
        "confidence": "中等",
        "score": 1,
        "details": {
          "kdj_score": -1,
          "macd_score": 1,
          "trend_score": 1,
          "pred_trend": 0.8475953285137804,
          "current_k": 73.13005637590354,
          "current_d": 70.77246039356962,
          "current_j": 77.84524834057137
        }
      }
    },
    {
      "stock_code": "002878",
      "timeframe": "daily",
      "prediction_date": "2025-11-20 13:42:42",
      "historical_data_points": 244,
      "pred_days": 5,
      "multi_model": {
        "technical": {
          "prices": [
            20.90328,
            20.94508656,
            20.98697673312,
            21.02895068658624,
            21.071008587959412
          ],
          "method": "technical_indicators",
          "signals": {
            "macd": 1,
            "rsi": -1,
            "ma": 1,
            "bollinger": -1
          }
        },
        "machine_learning": {
          "prices": [
            20.239400000000003,
            19.469600000000003,
            19.1316,
            20.021199999999993,
            19.485
          ],
          "method": "machine_learning",
          "model_type": "RandomForest"
        },
        "support_resistance": {
          "prices": [
            21.077939393939396,
            21.33587878787879,
            21.46717575757576,
            21.49343515151515,
            21.49868703030303
          ],
          "method": "support_resistance",
          "support_levels": [
            11.04,
            13.18,
            13.78,
            14.48,
            15.6
          ],
          "resistance_levels": [
            27.42,
            23.46,
            22.68,
            22.67,
            21.5
          ],
          "next_support": 15.6,
          "next_resistance": 21.5
        },
        "ensemble": {
          "prices": [
            20.69012581818182,
            20.472129604363637,
            20.38888574720873,
            20.76519575143041,
            20.56490868547873
          ],
          "method": "ensemble",
          "weights": {
            "technical": 0.3,
            "ml": 0.4,
            "support_resistance": 0.3
          }
        },
        "confidence": {
          "overall_confidence": 0.9646254910209175,
          "price_consistency": 0.9646254910209175,
          "std_deviation": 0.7305462085354816
        }
      },
      "summary": {
        "current_price": 20.82,
        "predicted_prices": [
          20.69012581818182,
          20.472129604363637,
          20.38888574720873,
          20.76519575143041,
          20.56490868547873
        ],
        "price_changes": [
          -0.129874181818181,
          -0.34787039563636313,
          -0.43111425279127147,
          -0.054804248569588765,
          -0.25509131452126965
        ],
        "price_change_pcts": [
          -0.6237953017203699,
          -1.6708472412889679,
          -2.0706736445306024,
          -0.26322885960417275,
          -1.2252224520714199
        ],
        "confidence": 0.9646254910209175
      },
      "trading_signal": {
        "recommendation": "少量买入",
        "confidence": "中等",
        "score": 0,
        "details": {
          "kdj_score": 0,
          "macd_score": 1,
          "trend_score": -1,
          "pred_trend": -0.6052023743280084,
          "current_k": 71.72806733684793,
          "current_d": 69.13398625013564,
          "current_j": 76.91622951027253
        }
      }
    },
    {
      "stock_code": "000066",
      "timeframe": "daily",
      "prediction_date": "2025-11-20 13:42:44",
      "historical_data_points": 244,
      "pred_days": 5,
      "multi_model": {
        "technical": {
          "prices": [
            15.51768,
            15.455609280000001,
            15.42469806144,
            15.39384866531712,
            15.363060967986486
          ],
          "method": "technical_indicators",
          "signals": {
            "macd": -1,
            "rsi": 1,
            "ma": -1,
            "bollinger": 1
          }
        },
        "machine_learning": {
          "prices": [
            15.5122,
            15.290000000000004,
            14.858400000000003,
            14.676800000000005,
            14.545000000000005
          ],
          "method": "machine_learning",
          "model_type": "RandomForest"
        },
        "support_resistance": {
          "prices": [
            15.535333333333332,
            15.490666666666664,
            15.445999999999996,
            15.401333333333328,
            15.35666666666666
          ],
          "method": "support_resistance",
          "support_levels": [
            12.91,
            13.0,
            13.01,
            13.76,
            14.1
          ],
          "resistance_levels": [
            19.75,
            19.16,
            18.49,
            18.37,
            18.15
          ],
          "next_support": 14.1,
          "next_resistance": 18.15
        },
        "ensemble": {
          "prices": [
            15.520783999999999,
            15.399882784000003,
            15.204569418432001,
            15.109274599595137,
            15.033918290395945
          ],
          "method": "ensemble",
          "weights": {
            "technical": 0.3,
            "ml": 0.4,
            "support_resistance": 0.3
          }
        },
        "confidence": {
          "overall_confidence": 0.9855913391955959,
          "price_consistency": 0.9855913391955959,
          "std_deviation": 0.2186866726047764
        }
      },
      "summary": {
        "current_price": 15.58,
        "predicted_prices": [
          15.520783999999999,
          15.399882784000003,
          15.204569418432001,
          15.109274599595137,
          15.033918290395945
        ],
        "price_changes": [
          -0.059216000000001046,
          -0.18011721599999753,
          -0.3754305815679988,
          -0.4707254004048629,
          -0.5460817096040547
        ],
        "price_change_pcts": [
          -0.3800770218228565,
          -1.1560796919126928,
          -2.4096956454942156,
          -3.0213440334073356,
          -3.5050173915536242
        ],
        "confidence": 0.9855913391955959
      },
      "trading_signal": {
        "recommendation": "观望",
        "confidence": "谨慎",
        "score": -1,
        "details": {
          "kdj_score": 2,
          "macd_score": -1,
          "trend_score": -2,
          "pred_trend": -3.1368628646855314,
          "current_k": 15.491167355382087,
          "current_d": 18.030721131606736,
          "current_j": 10.412059802932788
        }
      }
    },
    {
      "stock_code": "002842",
      "timeframe": "daily",
      "prediction_date": "2025-11-20 13:42:45",
      "historical_data_points": 244,
      "pred_days": 5,
      "multi_model": {
        "technical": {
          "prices": [
            11.56,
            11.56,
            11.56,
            11.56,
            11.56
          ],
          "method": "technical_indicators",
          "signals": {
            "macd": -1,
            "rsi": 0,
            "ma": 1,
            "bollinger": 0
          }
        },
        "machine_learning": {
          "prices": [
            11.208199999999994,
            10.7678,
            10.810399999999998,
            10.616599999999998,
            10.648200000000001
          ],
          "method": "machine_learning",
          "model_type": "RandomForest"
        },
        "support_resistance": {
          "prices": [
            11.591636363636365,
            11.62327272727273,
            11.636654545454546,
            11.63933090909091,
            11.639866181818183
          ],
          "method": "support_resistance",
          "support_levels": [
            5.72,
            5.77,
            6.34,
            6.49,
            6.5
          ],
          "resistance_levels": [
            13.53,
            12.78,
            11.64,
            10.17,
            9.6
          ],
          "next_support": 6.5,
          "next_resistance": 11.64
        },
        "ensemble": {
          "prices": [
            11.428770909090908,
            11.262101818181819,
            11.283156363636362,
            11.206439272727273,
            11.219239854545455
          ],
          "method": "ensemble",
          "weights": {
            "technical": 0.3,
            "ml": 0.4,
            "support_resistance": 0.3
          }
        },
        "confidence": {
          "overall_confidence": 0.9672939635606443,
          "price_consistency": 0.9672939635606443,
          "std_deviation": 0.3700261062282841
        }
      },
      "summary": {
        "current_price": 11.56,
        "predicted_prices": [
          11.428770909090908,
          11.262101818181819,
          11.283156363636362,
          11.206439272727273,
          11.219239854545455
        ],
        "price_changes": [
          -0.13122909090909296,
          -0.29789818181818184,
          -0.2768436363636386,
          -0.35356072727272725,
          -0.3407601454545457
        ],
        "price_change_pcts": [
          -1.135199748348555,
          -2.5769738911607427,
          -2.394841145014175,
          -3.0584837999370866,
          -2.9477521233092188
        ],
        "confidence": 0.9672939635606443
      },
      "trading_signal": {
        "recommendation": "观望",
        "confidence": "谨慎",
        "score": -1,
        "details": {
          "kdj_score": -1,
          "macd_score": 1,
          "trend_score": -1,
          "pred_trend": -1.8333647267247541,
          "current_k": 36.917692201412706,
          "current_d": 39.264196425950715,
          "current_j": 32.22468375233669
        }
      }
    },
    {
      "stock_code": "000665",
      "timeframe": "daily",
      "prediction_date": "2025-11-20 13:42:47",
      "historical_data_points": 244,
      "pred_days": 5,
      "multi_model": {
        "technical": {
          "prices": [
            6.11,
            6.11,
            6.11,
            6.11,
            6.11
          ],
          "method": "technical_indicators",
          "signals": {
            "macd": -1,
            "rsi": 0,
            "ma": 1,
            "bollinger": 0
          }
        },
        "machine_learning": {
          "prices": [
            6.079200000000002,
            6.078600000000002,
            6.0752,
            6.085399999999998,
            6.1264
          ],
          "method": "machine_learning",
          "model_type": "RandomForest"
        },
        "support_resistance": {
          "prices": [
            6.10509090909091,
            6.100181818181819,
            6.095272727272729,
            6.090363636363638,
            6.085454545454548
          ],
          "method": "support_resistance",
          "support_levels": [
            3.52,
            3.75,
            3.95,
            4.04,
            4.15
          ],
          "resistance_levels": [
            7.72,
            6.99,
            6.86,
            6.65,
            6.64
          ],
          "next_support": 4.15,
          "next_resistance": 6.64
        },
        "ensemble": {
          "prices": [
            6.096207272727274,
            6.0944945454545465,
            6.091661818181819,
            6.094269090909091,
            6.109196363636364
          ],
          "method": "ensemble",
          "weights": {
            "technical": 0.3,
            "ml": 0.4,
            "support_resistance": 0.3
          }
        },
        "confidence": {
          "overall_confidence": 0.9977589157674833,
          "price_consistency": 0.9977589157674833,
          "std_deviation": 0.013667474514899358
        }
      },
      "summary": {
        "current_price": 6.11,
        "predicted_prices": [
          6.096207272727274,
          6.0944945454545465,
          6.091661818181819,
          6.094269090909091,
          6.109196363636364
        ],
        "price_changes": [
          -0.013792727272726069,
          -0.015505454545453823,
          -0.01833818181818092,
          -0.015730909090909684,
          -0.0008036363636358956
        ],
        "price_change_pcts": [
          -0.22574021722955923,
          -0.253771760154727,
          -0.3001339086445322,
          -0.257461687248931,
          -0.013152804642158684
        ],
        "confidence": 0.9977589157674833
      },
      "trading_signal": {
        "recommendation": "观望",
        "confidence": "谨慎",
        "score": -1,
        "details": {
          "kdj_score": 1,
          "macd_score": -2,
          "trend_score": 0,
          "pred_trend": 0.21306839364205565,
          "current_k": 32.15110799501804,
          "current_d": 52.23828090535157,
          "current_j": 0.0
        }
      }
    },
    {
      "stock_code": "002466",
      "timeframe": "daily",
      "prediction_date": "2025-11-20 13:42:50",
      "historical_data_points": 244,
      "pred_days": 5,
      "multi_model": {
        "technical": {
          "prices": [
            63.96148,
            64.34524888,
            64.73132037328,
            64.99024565477312,
            65.25020663739221
          ],
          "method": "technical_indicators",
          "signals": {
            "macd": 1,
            "rsi": 0,
            "ma": 1,
            "bollinger": -1
          }
        },
        "machine_learning": {
          "prices": [
            57.7054,
            57.318400000000004,
            56.12659999999999,
            56.0572,
            57.525999999999996
          ],
          "method": "machine_learning",
          "model_type": "RandomForest"
        },
        "support_resistance": {
          "prices": [
            64.46715151515151,
            65.35430303030303,
            66.24145454545454,
            66.65549090909091,
            66.73829818181818
          ],
          "method": "support_resistance",
          "support_levels": [
            25.57,
            27.2,
            28.57,
            28.84,
            29.21
          ],
          "resistance_levels": [
            52.2,
            49.67,
            47.1,
            44.88,
            42.94
          ],
          "next_support": 29.21,
          "next_resistance": 66.759
        },
        "ensemble": {
          "prices": [
            61.610749454545456,
            61.83722557309091,
            61.74247247562036,
            61.91660096915921,
            62.606951445763116
          ],
          "method": "ensemble",
          "weights": {
            "technical": 0.3,
            "ml": 0.4,
            "support_resistance": 0.3
          }
        },
        "confidence": {
          "overall_confidence": 0.9366741442989723,
          "price_consistency": 0.9366741442989723,
          "std_deviation": 3.959192666653702
        }
      },
      "summary": {
        "current_price": 63.58,
        "predicted_prices": [
          61.610749454545456,
          61.83722557309091,
          61.74247247562036,
          61.91660096915921,
          62.606951445763116
        ],
        "price_changes": [
          -1.9692505454545426,
          -1.7427744269090866,
          -1.837527524379638,
          -1.663399030840786,
          -0.9730485542368825
        ],
        "price_change_pcts": [
          -3.0972798764620046,
          -2.7410733358117123,
          -2.8901030581623752,
          -2.61622999503112,
          -1.5304318248456787
        ],
        "confidence": 0.9366741442989723
      },
      "trading_signal": {
        "recommendation": "少量买入",
        "confidence": "中等",
        "score": 1,
        "details": {
          "kdj_score": -1,
          "macd_score": 1,
          "trend_score": 1,
          "pred_trend": 1.6169288639357127,
          "current_k": 79.13312700715504,
          "current_d": 76.40925788354156,
          "current_j": 84.58086525438199
        }
      }
    },
    {
      "stock_code": "002460",
      "timeframe": "daily",
      "prediction_date": "2025-11-20 13:43:04",
      "historical_data_points": 0,
      "pred_days": 5,
      "error": "无法从网络获取股票 002460 的历史数据，请检查网络连接或股票代码是否正确"
    },
    {
      "stock_code": "601899",
      "timeframe": "daily",
      "prediction_date": "2025-11-20 13:43:09",
      "historical_data_points": 0,
      "pred_days": 5,
      "error": "无法从网络获取股票 601899 的历史数据，请检查网络连接或股票代码是否正确"
    },
    {
      "stock_code": "600491",
      "timeframe": "daily",
      "prediction_date": "2025-11-20 13:43:14",
      "historical_data_points": 0,
      "pred_days": 5,
      "error": "无法从网络获取股票 600491 的历史数据，请检查网络连接或股票代码是否正确"
    },
    {
      "stock_code": "000156",
      "timeframe": "daily",
      "prediction_date": "2025-11-20 13:43:18",
      "historical_data_points": 0,
      "pred_days": 5,
      "error": "无法从网络获取股票 000156 的历史数据，请检查网络连接或股票代码是否正确"
    },
    {
      "stock_code": "002044",
      "timeframe": "daily",
      "prediction_date": "2025-11-20 13:43:24",
      "historical_data_points": 0,
      "pred_days": 5,
      "error": "无法从网络获取股票 002044 的历史数据，请检查网络连接或股票代码是否正确"
    },
    {
      "stock_code": "002198",
      "timeframe": "daily",
      "prediction_date": "2025-11-20 13:43:30",
      "historical_data_points": 0,
      "pred_days": 5,
      "error": "无法从网络获取股票 002198 的历史数据，请检查网络连接或股票代码是否正确"
    }
  ]
}